src/fastopendata-client/__init__.py
src/fastopendata-client/client.py
fastopendata-0.0.4.dist-info/METADATA
fastopendata-0.0.4.dist-info/WHEEL
fastopendata-0.0.4.dist-info/licenses/LICENSE
fastopendata-0.0.4.dist-info/RECORD
