Metadata-Version: 2.1
Name: fastopendata
Version: 0.0.4
Summary: Client for the FastOpenData API service
Project-URL: Homepage, https://github.com/zacernst/fastopendata-client
Project-URL: Bug Tracker, https://github.com/zacernst/fastopendata-client/issues
Author-email: Zachary Ernst <zac.ernst@gmail.com>
License-File: LICENSE
Classifier: License :: OSI Approved :: MIT License
Classifier: Operating System :: OS Independent
Classifier: Programming Language :: Python :: 3
Requires-Python: >=3.7
